README.rst
setup.py
sadcat/__init__.py
sadcat/sadcat.py
sadcat.egg-info/PKG-INFO
sadcat.egg-info/SOURCES.txt
sadcat.egg-info/dependency_links.txt
sadcat.egg-info/entry_points.txt
sadcat.egg-info/requires.txt
sadcat.egg-info/top_level.txt
sadcat.egg-info/zip-safe