Metadata-Version: 1.1
Name: sadcat
Version: 0.4.0
Summary: A ssh config generator I dont recommend to use
Home-page: https://github.com/noqqe/sadcat
Author: Florian Baumann
Author-email: flo@noqqe.de
License: MIT
Keywords: ssh config templating generator ssh_config toml
Platform: UNKNOWN
Classifier: Development Status :: 4 - Beta
Classifier: Topic :: Utilities
Classifier: Topic :: Terminals
Classifier: License :: OSI Approved :: MIT License
Classifier: Programming Language :: Python :: 2.7
Classifier: Programming Language :: Python :: 3.5
